<annotation>
	<folder>polluted</folder>
	<filename>WX20250603-163554@2x.png</filename>
	<path>/Users/jiahaifeng/Projects/oil recog/dataset/polluted/WX20250603-163554@2x.png</path>
	<source>
		<database>Unknown</database>
	</source>
	<size>
		<width>902</width>
		<height>604</height>
		<depth>3</depth>
	</size>
	<segmented>0</segmented>
	<object>
		<name>oil</name>
		<pose>Unspecified</pose>
		<truncated>0</truncated>
		<difficult>0</difficult>
		<bndbox>
			<xmin>62</xmin>
			<ymin>60</ymin>
			<xmax>360</xmax>
			<ymax>223</ymax>
		</bndbox>
	</object>
</annotation>
